<edmx:Edmx
    xmlns:edmx="http://schemas.microsoft.com/ado/2007/06/edmx"
    xmlns:m="http://schemas.microsoft.com/ado/2007/08/dataservices/metadata"
    xmlns:sap="http://www.sap.com/Protocols/SAPData" Version="1.0">
    <edmx:DataServices m:DataServiceVersion="2.0">
        <Schema
            xmlns="http://schemas.microsoft.com/ado/2008/09/edm" Namespace="ZGW_WM_BIN_TO_BIN010_SRV" xml:lang="en" sap:schema-version="1">
            <EntityType Name="ZStockMovement" sap:content-version="1">
                <Key>
                    <PropertyRef Name="Barcode"/>
                </Key>
                <Property Name="Valid_DestnNum_Result" Type="Edm.String" Nullable="false" sap:unicode="false" sap:creatable="false" sap:updatable="false" sap:sortable="false" sap:filterable="false"/>
                <Property Name="Barcode" Type="Edm.String" Nullable="false" sap:unicode="false" sap:creatable="false" sap:updatable="false" sap:sortable="false" sap:filterable="false"/>
                <Property Name="Decimal_sep" Type="Edm.String" Nullable="false" sap:unicode="false" sap:creatable="false" sap:updatable="false" sap:sortable="false" sap:filterable="false"/>
                <Property Name="DestnNum" Type="Edm.String" Nullable="false" sap:unicode="false" sap:creatable="false" sap:updatable="false" sap:sortable="false" sap:filterable="false"/>
                <Property Name="Thousand_sep" Type="Edm.String" Nullable="false" sap:unicode="false" sap:creatable="false" sap:updatable="false" sap:sortable="false" sap:filterable="false"/>
                <Property Name="Category" Type="Edm.String" Nullable="false" sap:unicode="false" sap:creatable="false" sap:updatable="false" sap:sortable="false" sap:filterable="false"/>
                <Property Name="StorageLocation" Type="Edm.String" Nullable="false" sap:unicode="false" sap:creatable="false" sap:updatable="false" sap:sortable="false" sap:filterable="false"/>
                <Property Name="Quantity" Type="Edm.Decimal" Nullable="false" Precision="13" Scale="3" sap:unicode="false" sap:creatable="false" sap:updatable="false" sap:sortable="false" sap:filterable="false"/>
                <Property Name="SourceBin" Type="Edm.String" Nullable="false" sap:unicode="false" sap:creatable="false" sap:updatable="false" sap:sortable="false" sap:filterable="false"/>
                <Property Name="MaterialNumber" Type="Edm.String" Nullable="false" sap:unicode="false" sap:creatable="false" sap:updatable="false" sap:sortable="false" sap:filterable="false"/>
                <Property Name="Sonum" Type="Edm.String" Nullable="false" sap:unicode="false" sap:creatable="false" sap:updatable="false" sap:sortable="false" sap:filterable="false"/>
                <Property Name="BatchNumber" Type="Edm.String" Nullable="false" sap:unicode="false" sap:creatable="false" sap:updatable="false" sap:sortable="false" sap:filterable="false"/>
                <Property Name="Sobkz" Type="Edm.String" Nullable="false" sap:unicode="false" sap:creatable="false" sap:updatable="false" sap:sortable="false" sap:filterable="false"/>
                <Property Name="Tanum" Type="Edm.String" Nullable="false" sap:unicode="false" sap:creatable="false" sap:updatable="false" sap:sortable="false" sap:filterable="false"/>
                <Property Name="UOM" Type="Edm.String" Nullable="false" sap:unicode="false" sap:creatable="false" sap:updatable="false" sap:sortable="false" sap:filterable="false"/>
                <Property Name="MESNumber" Type="Edm.String" Nullable="false" sap:unicode="false" sap:creatable="false" sap:updatable="false" sap:sortable="false" sap:filterable="false"/>
                <Property Name="Res" Type="Edm.String" Nullable="false" sap:unicode="false" sap:creatable="false" sap:updatable="false" sap:sortable="false" sap:filterable="false"/>
            </EntityType>
            <EntityContainer Name="ZGW_WM_BIN_TO_BIN010_SRV_Entities" m:IsDefaultEntityContainer="true" sap:supported-formats="atom json">
                <EntitySet Name="ZStockMovementCollection" EntityType="ZGW_WM_BIN_TO_BIN010_SRV.ZStockMovement" sap:pageable="false" sap:content-version="1"/>
                <FunctionImport Name="ZValidateBin" ReturnType="Collection(ZGW_WM_BIN_TO_BIN010_SRV.ZStockMovement)" EntitySet="ZStockMovementCollection" m:HttpMethod="GET">
                    <Parameter Name="DestnNum" Type="Edm.String" Mode="In"/>
                </FunctionImport>
            </EntityContainer>
            <atom:link
                xmlns:atom="http://www.w3.org/2005/Atom" rel="self" href="./sap/ZGW_WM_BIN_TO_BIN010_SRV/$metadata"/>
                <atom:link
                    xmlns:atom="http://www.w3.org/2005/Atom" rel="latest-version" href="./sap/ZGW_WM_BIN_TO_BIN010_SRV/$metadata"/>
                </Schema>
            </edmx:DataServices>
        </edmx:Edmx>